LICENSE.rst
MANIFEST.in
README.rst
setup.py
src/node/__init__.py
src/node.ext.zcml.egg-info/PKG-INFO
src/node.ext.zcml.egg-info/SOURCES.txt
src/node.ext.zcml.egg-info/dependency_links.txt
src/node.ext.zcml.egg-info/entry_points.txt
src/node.ext.zcml.egg-info/namespace_packages.txt
src/node.ext.zcml.egg-info/not-zip-safe
src/node.ext.zcml.egg-info/requires.txt
src/node.ext.zcml.egg-info/top_level.txt
src/node/ext/__init__.py
src/node/ext/zcml/__init__.py
src/node/ext/zcml/_api.py
src/node/ext/zcml/_api.rst
src/node/ext/zcml/interfaces.py
src/node/ext/zcml/tests.py
src/node/ext/zcml/testing/__init__.py
src/node/ext/zcml/testing/data/configure.zcml
src/node/ext/zcml/testing/data/dumped.configure.zcml
src/node/ext/zcml/testing/data/modified.zcml
src/node/ext/zcml/testing/data/new.zcml